{
  "configVersion": 1,
  "timestamp": 1627231363499,
  "index": "https://abhi-wat101.github.io/demo1/index.html",
  "assetGroups": [
    {
      "name": "app",
      "installMode": "prefetch",
      "updateMode": "prefetch",
      "cacheQueryOptions": {
        "ignoreVary": true
      },
      "urls": [
        "https://abhi-wat101.github.io/demo1/favicon.ico",
        "https://abhi-wat101.github.io/demo1/index.html",
        "https://abhi-wat101.github.io/demo1/main.44bb097981ebb29b73ac.js",
        "https://abhi-wat101.github.io/demo1/manifest.webmanifest",
        "https://abhi-wat101.github.io/demo1/polyfills.12b09180c31a95efd622.js",
        "https://abhi-wat101.github.io/demo1/runtime.43bf3493b057b10a9e88.js",
        "https://abhi-wat101.github.io/demo1/scripts.5ecbcd3c04814cc0c85b.js",
        "https://abhi-wat101.github.io/demo1/styles.e42d59c68ff1b657ae54.css"
      ],
      "patterns": []
    },
    {
      "name": "assets",
      "installMode": "lazy",
      "updateMode": "prefetch",
      "cacheQueryOptions": {
        "ignoreVary": true
      },
      "urls": [
        "https://abhi-wat101.github.io/demo1/assets/icons/apple-touch-icon-ipad-76x76.png",
        "https://abhi-wat101.github.io/demo1/assets/icons/apple-touch-icon-ipad-retina-152x152.png",
        "https://abhi-wat101.github.io/demo1/assets/icons/apple-touch-icon-iphone-60x60.png",
        "https://abhi-wat101.github.io/demo1/assets/icons/apple-touch-icon-iphone-retina-120x120.png",
        "https://abhi-wat101.github.io/demo1/assets/icons/icon-128x128.png",
        "https://abhi-wat101.github.io/demo1/assets/icons/icon-144x144.png",
        "https://abhi-wat101.github.io/demo1/assets/icons/icon-152x152.png",
        "https://abhi-wat101.github.io/demo1/assets/icons/icon-192x192.png",
        "https://abhi-wat101.github.io/demo1/assets/icons/icon-384x384.png",
        "https://abhi-wat101.github.io/demo1/assets/icons/icon-512x512.png",
        "https://abhi-wat101.github.io/demo1/assets/icons/icon-72x72.png",
        "https://abhi-wat101.github.io/demo1/assets/icons/icon-96x96.png",
        "https://abhi-wat101.github.io/demo1/assets/images/Fav_1_32_32.png",
        "https://abhi-wat101.github.io/demo1/assets/images/Fav_2_32_32.png",
        "https://abhi-wat101.github.io/demo1/assets/images/Group 1281@2x.png",
        "https://abhi-wat101.github.io/demo1/assets/images/Icon feather-filter.svg",
        "https://abhi-wat101.github.io/demo1/assets/images/Icon-feather-home.png",
        "https://abhi-wat101.github.io/demo1/assets/images/Icon-ionic-ios-search.png",
        "https://abhi-wat101.github.io/demo1/assets/images/bannerDefault.jpg",
        "https://abhi-wat101.github.io/demo1/assets/images/bannerDefaultMob.jpg",
        "https://abhi-wat101.github.io/demo1/assets/images/chevron-next.png",
        "https://abhi-wat101.github.io/demo1/assets/images/chevron-prev.png",
        "https://abhi-wat101.github.io/demo1/assets/images/dashed_slider.png",
        "https://abhi-wat101.github.io/demo1/assets/images/default-logo.jpg",
        "https://abhi-wat101.github.io/demo1/assets/images/eye2.png",
        "https://abhi-wat101.github.io/demo1/assets/images/favicon.ico",
        "https://abhi-wat101.github.io/demo1/assets/images/favicon.png",
        "https://abhi-wat101.github.io/demo1/assets/images/greentick.png",
        "https://abhi-wat101.github.io/demo1/assets/images/location.png",
        "https://abhi-wat101.github.io/demo1/assets/images/location.svg",
        "https://abhi-wat101.github.io/demo1/assets/images/logo.svg",
        "https://abhi-wat101.github.io/demo1/assets/images/logoLoad.png",
        "https://abhi-wat101.github.io/demo1/assets/images/logoLoad2x.png",
        "https://abhi-wat101.github.io/demo1/assets/images/pharmacy.png",
        "https://abhi-wat101.github.io/demo1/assets/images/rectangle_169.png",
        "https://abhi-wat101.github.io/demo1/assets/images/tick.png",
        "https://abhi-wat101.github.io/demo1/assets/images/tickgrey.png",
        "https://abhi-wat101.github.io/demo1/assets/images/vacc.jpg",
        "https://abhi-wat101.github.io/demo1/assets/images/wrong.png",
        "https://abhi-wat101.github.io/demo1/assets/policy/ItsMyPharma Privacy Policy_13032021.pdf",
        "https://abhi-wat101.github.io/demo1/assets/policy/ItsMyPharma Terms of Service_13032021.pdf",
        "https://abhi-wat101.github.io/demo1/assets/policy/Privacy Policy_09022021.pdf",
        "https://abhi-wat101.github.io/demo1/assets/policy/Terms of Service_09022021.pdf",
        "https://abhi-wat101.github.io/demo1/chevron-next.3113ef60c1edca34f35b.png",
        "https://abhi-wat101.github.io/demo1/chevron-prev.dc08f9bb0a2d291cd0f8.png",
        "https://abhi-wat101.github.io/demo1/fa-brands-400.216edb96b562c79adc09.svg",
        "https://abhi-wat101.github.io/demo1/fa-brands-400.329a95a9172fdb2cccb4.woff",
        "https://abhi-wat101.github.io/demo1/fa-brands-400.89a52ae1d02b86d61439.eot",
        "https://abhi-wat101.github.io/demo1/fa-brands-400.9e138496e8f1719c6ebf.ttf",
        "https://abhi-wat101.github.io/demo1/fa-brands-400.c1210e5ebe4344da5083.woff2",
        "https://abhi-wat101.github.io/demo1/fa-regular-400.1017bce89c72f95bcf8e.ttf",
        "https://abhi-wat101.github.io/demo1/fa-regular-400.19e27d348fefc21941e0.svg",
        "https://abhi-wat101.github.io/demo1/fa-regular-400.3672264812746c3c7225.woff",
        "https://abhi-wat101.github.io/demo1/fa-regular-400.4079ae2d2a15d0689568.eot",
        "https://abhi-wat101.github.io/demo1/fa-regular-400.68c5af1f48e2bfca1e57.woff2",
        "https://abhi-wat101.github.io/demo1/fa-solid-900.07c3313b24f7b1ca85ee.ttf",
        "https://abhi-wat101.github.io/demo1/fa-solid-900.13de59f1a36b6cb4bca0.svg",
        "https://abhi-wat101.github.io/demo1/fa-solid-900.ada6e6df937f7e5e8b79.woff2",
        "https://abhi-wat101.github.io/demo1/fa-solid-900.c6ec080084769a6d8a34.woff",
        "https://abhi-wat101.github.io/demo1/fa-solid-900.efbd5d20e407bbf85f2b.eot",
        "https://abhi-wat101.github.io/demo1/owl.video.play.7f01b07148f205f6e825.png"
      ],
      "patterns": []
    }
  ],
  "dataGroups": [],
  "hashTable": {
    "https://abhi-wat101.github.io/demo1/assets/icons/apple-touch-icon-ipad-76x76.png": "56df2b59dd8a8544348d26953dfed5c4ca132342",
    "https://abhi-wat101.github.io/demo1/assets/icons/apple-touch-icon-ipad-retina-152x152.png": "0ecca929d2b4fc958bf9d3a9e7179a4df009c0f5",
    "https://abhi-wat101.github.io/demo1/assets/icons/apple-touch-icon-iphone-60x60.png": "70ab1a5e88b6a5314541f065b9e9281f476e59b6",
    "https://abhi-wat101.github.io/demo1/assets/icons/apple-touch-icon-iphone-retina-120x120.png": "a521f1897354bdbdeb5663c34ae2098c239c63c9",
    "https://abhi-wat101.github.io/demo1/assets/icons/icon-128x128.png": "dae3b6ed49bdaf4327b92531d4b5b4a5d30c7532",
    "https://abhi-wat101.github.io/demo1/assets/icons/icon-144x144.png": "b0bd89982e08f9bd2b642928f5391915b74799a7",
    "https://abhi-wat101.github.io/demo1/assets/icons/icon-152x152.png": "7479a9477815dfd9668d60f8b3b2fba709b91310",
    "https://abhi-wat101.github.io/demo1/assets/icons/icon-192x192.png": "1abd80d431a237a853ce38147d8c63752f10933b",
    "https://abhi-wat101.github.io/demo1/assets/icons/icon-384x384.png": "329749cd6393768d3131ed6304c136b1ca05f2fd",
    "https://abhi-wat101.github.io/demo1/assets/icons/icon-512x512.png": "559d9c4318b45a1f2b10596bbb4c960fe521dbcc",
    "https://abhi-wat101.github.io/demo1/assets/icons/icon-72x72.png": "c457e56089a36952cd67156f9996bc4ce54a5ed9",
    "https://abhi-wat101.github.io/demo1/assets/icons/icon-96x96.png": "3914125a4b445bf111c5627875fc190f560daa41",
    "https://abhi-wat101.github.io/demo1/assets/images/Fav_1_32_32.png": "d88f0489a2d74f8db9e7ce66af2410a761642f3e",
    "https://abhi-wat101.github.io/demo1/assets/images/Fav_2_32_32.png": "9167f0a6a8f4a0af233f70b0aeef9e8c67af63be",
    "https://abhi-wat101.github.io/demo1/assets/images/Group 1281@2x.png": "a2529afff4a411d81d39d25d5a3e245eb8030b84",
    "https://abhi-wat101.github.io/demo1/assets/images/Icon feather-filter.svg": "82c66a8d262c459581197f40c00ab9a32488d62a",
    "https://abhi-wat101.github.io/demo1/assets/images/Icon-feather-home.png": "fdda816b0686a0786b5e424ea3e2695e537a3680",
    "https://abhi-wat101.github.io/demo1/assets/images/Icon-ionic-ios-search.png": "d01213384c19b5312e0c5bb502a97577e6cec022",
    "https://abhi-wat101.github.io/demo1/assets/images/bannerDefault.jpg": "33f9ed5f381026cbfabc9a2c38b91bf04366b2d6",
    "https://abhi-wat101.github.io/demo1/assets/images/bannerDefaultMob.jpg": "4c17bdcaa6b793b2c52afe319295ab29fac78037",
    "https://abhi-wat101.github.io/demo1/assets/images/chevron-next.png": "ea45dd8da90eccc3157a302d94027af063a85824",
    "https://abhi-wat101.github.io/demo1/assets/images/chevron-prev.png": "0ca1db796d71e1ca9fdd58bc9e24e3436d6ad425",
    "https://abhi-wat101.github.io/demo1/assets/images/dashed_slider.png": "4bcf30e16bf4dfb5132b620251238d0a875c1ec4",
    "https://abhi-wat101.github.io/demo1/assets/images/default-logo.jpg": "5ea21d750bd18482964bf82a1f789964c40d9884",
    "https://abhi-wat101.github.io/demo1/assets/images/eye2.png": "7e8d8b4fa130f0fdcee9749911c96028ad8a1222",
    "https://abhi-wat101.github.io/demo1/assets/images/favicon.ico": "6fa0016d85e8f87912205a34b2a2048c307c0e6c",
    "https://abhi-wat101.github.io/demo1/assets/images/favicon.png": "4e30824ef57851df712e0d82598f82c7c3f8c52f",
    "https://abhi-wat101.github.io/demo1/assets/images/greentick.png": "b1253c08ec988b76a35b4acae2403a328b207663",
    "https://abhi-wat101.github.io/demo1/assets/images/location.png": "75aa833cf59b0c1bf4e4d88dfad532ea6771b41b",
    "https://abhi-wat101.github.io/demo1/assets/images/location.svg": "8c72f30b2286b0de0a530292414ed678eb4a88bc",
    "https://abhi-wat101.github.io/demo1/assets/images/logo.svg": "710e2dd8a33a15b3e0cc1794cbe24e485c2849ae",
    "https://abhi-wat101.github.io/demo1/assets/images/logoLoad.png": "e01d290b0cac78be55e1e2bdcfa6bba818d38b59",
    "https://abhi-wat101.github.io/demo1/assets/images/logoLoad2x.png": "7b5916dadf75daba9bcfecb5569fe2a03b653853",
    "https://abhi-wat101.github.io/demo1/assets/images/pharmacy.png": "c31774da82e67701a4ceb4daba940d4856dd829e",
    "https://abhi-wat101.github.io/demo1/assets/images/rectangle_169.png": "da39a3ee5e6b4b0d3255bfef95601890afd80709",
    "https://abhi-wat101.github.io/demo1/assets/images/tick.png": "bf801bff4eca7a36feb321a33e0b4fc6831f6219",
    "https://abhi-wat101.github.io/demo1/assets/images/tickgrey.png": "dfd090256fab3013f57f7241f91302c0a5c3a933",
    "https://abhi-wat101.github.io/demo1/assets/images/vacc.jpg": "b867cec23e0b8ddbaafc53167a35d7b6eb0288a9",
    "https://abhi-wat101.github.io/demo1/assets/images/wrong.png": "c6c644e5c216348d60e6b3db1cad145f086b679d",
    "https://abhi-wat101.github.io/demo1/assets/policy/ItsMyPharma Privacy Policy_13032021.pdf": "4ad7205a163e41d31e65872b18cf63613c7ffe3f",
    "https://abhi-wat101.github.io/demo1/assets/policy/ItsMyPharma Terms of Service_13032021.pdf": "83e0cfa4d49f2f758d6e29a54e9a62641724295b",
    "https://abhi-wat101.github.io/demo1/assets/policy/Privacy Policy_09022021.pdf": "94b38d5963acbcc3a4aea5f9e45b3cbcd8b2c2e4",
    "https://abhi-wat101.github.io/demo1/assets/policy/Terms of Service_09022021.pdf": "b25ca333161795c63f4db9a94514a89b576d8d5c",
    "https://abhi-wat101.github.io/demo1/chevron-next.3113ef60c1edca34f35b.png": "ea45dd8da90eccc3157a302d94027af063a85824",
    "https://abhi-wat101.github.io/demo1/chevron-prev.dc08f9bb0a2d291cd0f8.png": "0ca1db796d71e1ca9fdd58bc9e24e3436d6ad425",
    "https://abhi-wat101.github.io/demo1/fa-brands-400.216edb96b562c79adc09.svg": "24aff44d36f6c4a6a08230474b546b29641c75d6",
    "https://abhi-wat101.github.io/demo1/fa-brands-400.329a95a9172fdb2cccb4.woff": "5f8cab91347c553c1eb87f9b527f6bee8a28e40d",
    "https://abhi-wat101.github.io/demo1/fa-brands-400.89a52ae1d02b86d61439.eot": "a400bc89d3cb4d45a3b90791800587a1e4ebafa6",
    "https://abhi-wat101.github.io/demo1/fa-brands-400.9e138496e8f1719c6ebf.ttf": "3fa2d67cef22da5c3f3eb5730c6afbd6fecf0372",
    "https://abhi-wat101.github.io/demo1/fa-brands-400.c1210e5ebe4344da5083.woff2": "fce0da592a3e536d6d5df5b50cb513398d8c5161",
    "https://abhi-wat101.github.io/demo1/fa-regular-400.1017bce89c72f95bcf8e.ttf": "7d849a3981a716e2ba4a84634bc57d0b8054a6a3",
    "https://abhi-wat101.github.io/demo1/fa-regular-400.19e27d348fefc21941e0.svg": "8d0198777d4c6ff9c39a387f212b4ef732f70abb",
    "https://abhi-wat101.github.io/demo1/fa-regular-400.3672264812746c3c7225.woff": "d33d8b5b15b7bba2cc17190dc685fe0a76d2989e",
    "https://abhi-wat101.github.io/demo1/fa-regular-400.4079ae2d2a15d0689568.eot": "894064dfd376fc245fe654723d6c81f625e01363",
    "https://abhi-wat101.github.io/demo1/fa-regular-400.68c5af1f48e2bfca1e57.woff2": "0447c6b10bbf73f97b23dcfd6e6a48510822cb6e",
    "https://abhi-wat101.github.io/demo1/fa-solid-900.07c3313b24f7b1ca85ee.ttf": "c1b9fae262f42868c075ac865a8ab34920e20a2c",
    "https://abhi-wat101.github.io/demo1/fa-solid-900.13de59f1a36b6cb4bca0.svg": "33fe5758f3992d8da2635c4fa230b54376dd18d1",
    "https://abhi-wat101.github.io/demo1/fa-solid-900.ada6e6df937f7e5e8b79.woff2": "a9922842a120a7f1eaced667480c5e185a106d69",
    "https://abhi-wat101.github.io/demo1/fa-solid-900.c6ec080084769a6d8a34.woff": "52751432ded489dfdf27fb1cf64c570c4c27a1d7",
    "https://abhi-wat101.github.io/demo1/fa-solid-900.efbd5d20e407bbf85f2b.eot": "b18bdd10beee0a20231aa4c9ea11e84a9307a4fd",
    "https://abhi-wat101.github.io/demo1/favicon.ico": "6fa0016d85e8f87912205a34b2a2048c307c0e6c",
    "https://abhi-wat101.github.io/demo1/index.html": "db6677e2aa4abd1be6cf02f6fda96082d2279e47",
    "https://abhi-wat101.github.io/demo1/main.44bb097981ebb29b73ac.js": "7cd37151b82a86cd1629a64010059dae1e56924e",
    "https://abhi-wat101.github.io/demo1/manifest.webmanifest": "2b154e6ecef3fc29e6f5b9c5d308be4c83c7b274",
    "https://abhi-wat101.github.io/demo1/owl.video.play.7f01b07148f205f6e825.png": "c0d64356ec2758cb280d183b4829c923e5ff61e5",
    "https://abhi-wat101.github.io/demo1/polyfills.12b09180c31a95efd622.js": "8ed5fbfa55062f9550a80804b8857b4b63738fab",
    "https://abhi-wat101.github.io/demo1/runtime.43bf3493b057b10a9e88.js": "8d9de8985926ef99d8684c6a812efe2fe3ea462d",
    "https://abhi-wat101.github.io/demo1/scripts.5ecbcd3c04814cc0c85b.js": "0d0eec7c8408c5c50fa355bd00ac9e8792612aa4",
    "https://abhi-wat101.github.io/demo1/styles.e42d59c68ff1b657ae54.css": "7cab8586df60d0b8340554743248ae0573d3efcf"
  },
  "navigationUrls": [
    {
      "positive": true,
      "regex": "^\\/.*$"
    },
    {
      "positive": false,
      "regex": "^\\/(?:.+\\/)?[^/]*\\.[^/]*$"
    },
    {
      "positive": false,
      "regex": "^\\/(?:.+\\/)?[^/]*__[^/]*$"
    },
    {
      "positive": false,
      "regex": "^\\/(?:.+\\/)?[^/]*__[^/]*\\/.*$"
    }
  ],
  "navigationRequestStrategy": "performance"
}